KyoPack/__init__.py
KyoPack-0.1.dist-info/LICENSE
KyoPack-0.1.dist-info/METADATA
KyoPack-0.1.dist-info/WHEEL
KyoPack-0.1.dist-info/entry_points.txt
KyoPack-0.1.dist-info/top_level.txt
KyoPack-0.1.dist-info/RECORD
