Metadata-Version: 2.1
Name: KyoPack
Version: 0.1
Summary: What I cannot create I do not understand!
Home-page: https://github.com/jojongx/KyoDai24_TrialPack
Author: Joseph Benigno
Author-email: jbenigno@ufl.edu
License: MIT
Platform: UNKNOWN
License-File: LICENSE
